{
	"$schema": "http://schema.management.azure.com/schemas/2015-01-01/deploymentTemplate.json#",
	"contentVersion": "1.0.0.0",
	"parameters": {
		"factoryName": {
			"type": "string",
			"metadata": "Data Factory name",
			"defaultValue": "TWADFTutorialDataFactory"
		}
	},
	"variables": {
		"factoryId": "[concat('Microsoft.DataFactory/factories/', parameters('factoryName'))]"
	},
	"resources": [
		{
			"name": "[concat(parameters('factoryName'), '/CopyFromBlobToSql')]",
			"type": "Microsoft.DataFactory/factories/pipelines",
			"apiVersion": "2018-06-01",
			"properties": {
				"activities": [
					{
						"name": "CopyFromBlobToSql",
						"type": "Copy",
						"dependsOn": [],
						"policy": {
							"timeout": "7.00:00:00",
							"retry": 0,
							"retryIntervalInSeconds": 30,
							"secureOutput": false,
							"secureInput": false
						},
						"userProperties": [],
						"typeProperties": {
							"source": {
								"type": "DelimitedTextSource",
								"storeSettings": {
									"type": "AzureBlobStorageReadSettings",
									"recursive": true,
									"enablePartitionDiscovery": false
								},
								"formatSettings": {
									"type": "DelimitedTextReadSettings"
								}
							},
							"sink": {
								"type": "AzureSqlSink",
								"preCopyScript": "--TRUNCATE TABLE [dbo].[emp]",
								"disableMetricsCollection": false
							},
							"enableStaging": false,
							"translator": {
								"type": "TabularTranslator",
								"typeConversion": true,
								"typeConversionSettings": {
									"allowDataTruncation": true,
									"treatBooleanAsNumber": false
								}
							}
						},
						"inputs": [
							{
								"referenceName": "DelimitedText1",
								"type": "DatasetReference",
								"parameters": {}
							}
						],
						"outputs": [
							{
								"referenceName": "AzureSqlTable1",
								"type": "DatasetReference",
								"parameters": {}
							}
						]
					}
				],
				"policy": {
					"elapsedTimeMetric": {},
					"cancelAfter": {}
				},
				"folder": {
					"name": "SimpleCopy"
				},
				"annotations": [],
				"lastPublishTime": "2021-07-06T02:15:27Z"
			},
			"dependsOn": []
		},
		{
			"name": "[concat(parameters('factoryName'), '/CopyFromBlobToSqlPipeline')]",
			"type": "Microsoft.DataFactory/factories/pipelines",
			"apiVersion": "2018-06-01",
			"properties": {
				"activities": [
					{
						"name": "CopyFromBlobToSqlPipeline",
						"type": "Copy",
						"dependsOn": [],
						"policy": {
							"timeout": "7.00:00:00",
							"retry": 0,
							"retryIntervalInSeconds": 30,
							"secureOutput": false,
							"secureInput": false
						},
						"userProperties": [],
						"typeProperties": {
							"source": {
								"type": "DelimitedTextSource",
								"storeSettings": {
									"type": "AzureBlobStorageReadSettings",
									"recursive": true,
									"enablePartitionDiscovery": false
								},
								"formatSettings": {
									"type": "DelimitedTextReadSettings"
								}
							},
							"sink": {
								"type": "AzureSqlSink"
							},
							"enableStaging": false,
							"translator": {
								"type": "TabularTranslator",
								"mappings": [
									{
										"source": {
											"name": "FirstName",
											"type": "String",
											"physicalType": "String"
										},
										"sink": {
											"name": "FirstName",
											"type": "String",
											"physicalType": "varchar"
										}
									},
									{
										"source": {
											"name": "LastName",
											"type": "String",
											"physicalType": "String"
										},
										"sink": {
											"name": "LastName",
											"type": "String",
											"physicalType": "varchar"
										}
									}
								],
								"typeConversion": true,
								"typeConversionSettings": {
									"allowDataTruncation": true,
									"treatBooleanAsNumber": false
								}
							}
						},
						"inputs": [
							{
								"referenceName": "DelimitedText2",
								"type": "DatasetReference",
								"parameters": {}
							}
						],
						"outputs": [
							{
								"referenceName": "AzureSqlTable1",
								"type": "DatasetReference",
								"parameters": {}
							}
						]
					}
				],
				"policy": {
					"elapsedTimeMetric": {},
					"cancelAfter": {}
				},
				"folder": {
					"name": "SimpleCopy"
				},
				"annotations": [],
				"lastPublishTime": "2021-07-06T02:15:27Z"
			},
			"dependsOn": []
		},
		{
			"name": "[concat(parameters('factoryName'), '/CopyJsonfilefromBlobtoAzureSQL')]",
			"type": "Microsoft.DataFactory/factories/pipelines",
			"apiVersion": "2018-06-01",
			"properties": {
				"activities": [
					{
						"name": "CopydatafromJson",
						"type": "Copy",
						"dependsOn": [],
						"policy": {
							"timeout": "7.00:00:00",
							"retry": 0,
							"retryIntervalInSeconds": 30,
							"secureOutput": false,
							"secureInput": false
						},
						"userProperties": [
							{
								"name": "Source",
								"value": "input//jsonfilewithhierarchy-100.json"
							},
							{
								"name": "Destination",
								"value": "."
							}
						],
						"typeProperties": {
							"source": {
								"type": "JsonSource",
								"storeSettings": {
									"type": "AzureBlobStorageReadSettings",
									"recursive": true,
									"enablePartitionDiscovery": false
								},
								"formatSettings": {
									"type": "JsonReadSettings"
								}
							},
							"sink": {
								"type": "AzureSqlSink",
								"tableOption": "autoCreate",
								"disableMetricsCollection": false
							},
							"enableStaging": false,
							"translator": {
								"type": "TabularTranslator",
								"mappings": [
									{
										"source": {
											"path": "[['firstName']"
										},
										"sink": {
											"name": "firstName"
										}
									},
									{
										"source": {
											"path": "[['lastName']"
										},
										"sink": {
											"name": "lastName"
										}
									},
									{
										"source": {
											"path": "[['gender']"
										},
										"sink": {
											"name": "gender"
										}
									},
									{
										"source": {
											"path": "[['age']"
										},
										"sink": {
											"name": "age"
										}
									},
									{
										"source": {
											"path": "[['number']"
										},
										"sink": {
											"name": "number"
										}
									}
								],
								"collectionReference": "$['people']"
							}
						},
						"inputs": [
							{
								"referenceName": "Json1",
								"type": "DatasetReference",
								"parameters": {}
							}
						],
						"outputs": [
							{
								"referenceName": "AzureSqlTable2",
								"type": "DatasetReference",
								"parameters": {}
							}
						]
					}
				],
				"policy": {
					"elapsedTimeMetric": {},
					"cancelAfter": {}
				},
				"folder": {
					"name": "SimpleCopy"
				},
				"annotations": [],
				"lastPublishTime": "2021-07-06T02:15:27Z"
			},
			"dependsOn": []
		},
		{
			"name": "[concat(parameters('factoryName'), '/Lab1')]",
			"type": "Microsoft.DataFactory/factories/pipelines",
			"apiVersion": "2018-06-01",
			"properties": {
				"activities": [
					{
						"name": "Data Movement Lab",
						"type": "Copy",
						"dependsOn": [],
						"policy": {
							"timeout": "7.00:00:00",
							"retry": 0,
							"retryIntervalInSeconds": 30,
							"secureOutput": false,
							"secureInput": false
						},
						"userProperties": [],
						"typeProperties": {
							"source": {
								"type": "AzureSqlSource",
								"queryTimeout": "02:00:00",
								"partitionOption": "None"
							},
							"sink": {
								"type": "DelimitedTextSink",
								"storeSettings": {
									"type": "AzureBlobStorageWriteSettings"
								},
								"formatSettings": {
									"type": "DelimitedTextWriteSettings",
									"quoteAllText": true,
									"fileExtension": ".txt"
								}
							},
							"enableStaging": false,
							"parallelCopies": 1,
							"translator": {
								"type": "TabularTranslator",
								"mappings": [
									{
										"source": {
											"name": "CustomerKey",
											"type": "Int32",
											"physicalType": "int"
										},
										"sink": {
											"name": "CustomerKey",
											"type": "String",
											"physicalType": "String"
										}
									},
									{
										"source": {
											"name": "GeographyKey",
											"type": "Int32",
											"physicalType": "int"
										},
										"sink": {
											"name": "GeographyKey",
											"type": "String",
											"physicalType": "String"
										}
									},
									{
										"source": {
											"name": "CustomerAlternateKey",
											"type": "String",
											"physicalType": "nvarchar"
										},
										"sink": {
											"name": "CustomerAlternateKey",
											"type": "String",
											"physicalType": "String"
										}
									},
									{
										"source": {
											"name": "Title",
											"type": "String",
											"physicalType": "nvarchar"
										},
										"sink": {
											"name": "Title",
											"type": "String",
											"physicalType": "String"
										}
									},
									{
										"source": {
											"name": "FirstName",
											"type": "String",
											"physicalType": "nvarchar"
										},
										"sink": {
											"name": "FirstName",
											"type": "String",
											"physicalType": "String"
										}
									},
									{
										"source": {
											"name": "MiddleName",
											"type": "String",
											"physicalType": "nvarchar"
										},
										"sink": {
											"name": "MiddleName",
											"type": "String",
											"physicalType": "String"
										}
									},
									{
										"source": {
											"name": "LastName",
											"type": "String",
											"physicalType": "nvarchar"
										},
										"sink": {
											"name": "LastName",
											"type": "String",
											"physicalType": "String"
										}
									},
									{
										"source": {
											"name": "NameStyle",
											"type": "Boolean",
											"physicalType": "bit"
										},
										"sink": {
											"name": "NameStyle",
											"type": "String",
											"physicalType": "String"
										}
									},
									{
										"source": {
											"name": "BirthDate",
											"type": "DateTime",
											"physicalType": "date"
										},
										"sink": {
											"name": "BirthDate",
											"type": "String",
											"physicalType": "String"
										}
									},
									{
										"source": {
											"name": "MaritalStatus",
											"type": "String",
											"physicalType": "nchar"
										},
										"sink": {
											"name": "MaritalStatus",
											"type": "String",
											"physicalType": "String"
										}
									},
									{
										"source": {
											"name": "Suffix",
											"type": "String",
											"physicalType": "nvarchar"
										},
										"sink": {
											"name": "Suffix",
											"type": "String",
											"physicalType": "String"
										}
									},
									{
										"source": {
											"name": "Gender",
											"type": "String",
											"physicalType": "nvarchar"
										},
										"sink": {
											"name": "Gender",
											"type": "String",
											"physicalType": "String"
										}
									},
									{
										"source": {
											"name": "EmailAddress",
											"type": "String",
											"physicalType": "nvarchar"
										},
										"sink": {
											"name": "EmailAddress",
											"type": "String",
											"physicalType": "String"
										}
									},
									{
										"source": {
											"name": "YearlyIncome",
											"type": "Decimal",
											"physicalType": "money",
											"scale": 4,
											"precision": 19
										},
										"sink": {
											"name": "YearlyIncome",
											"type": "String",
											"physicalType": "String"
										}
									},
									{
										"source": {
											"name": "TotalChildren",
											"type": "Byte",
											"physicalType": "tinyint"
										},
										"sink": {
											"name": "TotalChildren",
											"type": "String",
											"physicalType": "String"
										}
									},
									{
										"source": {
											"name": "NumberChildrenAtHome",
											"type": "Byte",
											"physicalType": "tinyint"
										},
										"sink": {
											"name": "NumberChildrenAtHome",
											"type": "String",
											"physicalType": "String"
										}
									},
									{
										"source": {
											"name": "EnglishEducation",
											"type": "String",
											"physicalType": "nvarchar"
										},
										"sink": {
											"name": "EnglishEducation",
											"type": "String",
											"physicalType": "String"
										}
									},
									{
										"source": {
											"name": "SpanishEducation",
											"type": "String",
											"physicalType": "nvarchar"
										},
										"sink": {
											"name": "SpanishEducation",
											"type": "String",
											"physicalType": "String"
										}
									},
									{
										"source": {
											"name": "FrenchEducation",
											"type": "String",
											"physicalType": "nvarchar"
										},
										"sink": {
											"name": "FrenchEducation",
											"type": "String",
											"physicalType": "String"
										}
									},
									{
										"source": {
											"name": "EnglishOccupation",
											"type": "String",
											"physicalType": "nvarchar"
										},
										"sink": {
											"name": "EnglishOccupation",
											"type": "String",
											"physicalType": "String"
										}
									},
									{
										"source": {
											"name": "SpanishOccupation",
											"type": "String",
											"physicalType": "nvarchar"
										},
										"sink": {
											"name": "SpanishOccupation",
											"type": "String",
											"physicalType": "String"
										}
									},
									{
										"source": {
											"name": "FrenchOccupation",
											"type": "String",
											"physicalType": "nvarchar"
										},
										"sink": {
											"name": "FrenchOccupation",
											"type": "String",
											"physicalType": "String"
										}
									},
									{
										"source": {
											"name": "HouseOwnerFlag",
											"type": "String",
											"physicalType": "nchar"
										},
										"sink": {
											"name": "HouseOwnerFlag",
											"type": "String",
											"physicalType": "String"
										}
									},
									{
										"source": {
											"name": "NumberCarsOwned",
											"type": "Byte",
											"physicalType": "tinyint"
										},
										"sink": {
											"name": "NumberCarsOwned",
											"type": "String",
											"physicalType": "String"
										}
									},
									{
										"source": {
											"name": "AddressLine1",
											"type": "String",
											"physicalType": "nvarchar"
										},
										"sink": {
											"name": "AddressLine1",
											"type": "String",
											"physicalType": "String"
										}
									},
									{
										"source": {
											"name": "AddressLine2",
											"type": "String",
											"physicalType": "nvarchar"
										},
										"sink": {
											"name": "AddressLine2",
											"type": "String",
											"physicalType": "String"
										}
									},
									{
										"source": {
											"name": "Phone",
											"type": "String",
											"physicalType": "nvarchar"
										},
										"sink": {
											"name": "Phone",
											"type": "String",
											"physicalType": "String"
										}
									},
									{
										"source": {
											"name": "DateFirstPurchase",
											"type": "DateTime",
											"physicalType": "date"
										},
										"sink": {
											"name": "DateFirstPurchase",
											"type": "String",
											"physicalType": "String"
										}
									},
									{
										"source": {
											"name": "CommuteDistance",
											"type": "String",
											"physicalType": "nvarchar"
										},
										"sink": {
											"name": "CommuteDistance",
											"type": "String",
											"physicalType": "String"
										}
									}
								],
								"typeConversion": true,
								"typeConversionSettings": {
									"allowDataTruncation": true,
									"treatBooleanAsNumber": false
								}
							}
						},
						"inputs": [
							{
								"referenceName": "AzureSQLPracticeDBDimCustomer",
								"type": "DatasetReference",
								"parameters": {}
							}
						],
						"outputs": [
							{
								"referenceName": "DataMovementLabBlob",
								"type": "DatasetReference",
								"parameters": {}
							}
						]
					}
				],
				"policy": {
					"elapsedTimeMetric": {},
					"cancelAfter": {}
				},
				"folder": {
					"name": "Data Movement Lab"
				},
				"annotations": [],
				"lastPublishTime": "2021-07-09T09:37:22Z"
			},
			"dependsOn": []
		},
		{
			"name": "[concat(parameters('factoryName'), '/ParametersExpressionsLab1')]",
			"type": "Microsoft.DataFactory/factories/pipelines",
			"apiVersion": "2018-06-01",
			"properties": {
				"activities": [
					{
						"name": "Get Metadata1",
						"type": "GetMetadata",
						"dependsOn": [],
						"policy": {
							"timeout": "7.00:00:00",
							"retry": 0,
							"retryIntervalInSeconds": 30,
							"secureOutput": false,
							"secureInput": false
						},
						"userProperties": [],
						"typeProperties": {
							"dataset": {
								"referenceName": "ParametersExpressionsLab",
								"type": "DatasetReference",
								"parameters": {}
							},
							"fieldList": [
								"itemName",
								"lastModified",
								"size"
							],
							"storeSettings": {
								"type": "AzureBlobStorageReadSettings",
								"recursive": true,
								"enablePartitionDiscovery": false
							},
							"formatSettings": {
								"type": "DelimitedTextReadSettings"
							}
						}
					},
					{
						"name": "Set variable1",
						"type": "SetVariable",
						"dependsOn": [
							{
								"activity": "Get Metadata1",
								"dependencyConditions": [
									"Succeeded"
								]
							}
						],
						"userProperties": [],
						"typeProperties": {
							"variableName": "test",
							"value": {
								"value": "@activity( 'Get Metadata1' ).output.lastModified",
								"type": "Expression"
							}
						}
					}
				],
				"policy": {
					"elapsedTimeMetric": {},
					"cancelAfter": {}
				},
				"variables": {
					"test": {
						"type": "String"
					}
				},
				"folder": {
					"name": "ParametersExpressionsLab"
				},
				"annotations": [],
				"lastPublishTime": "2021-07-02T07:26:56Z"
			},
			"dependsOn": []
		},
		{
			"name": "[concat(parameters('factoryName'), '/ParametersExpressionsLab2')]",
			"type": "Microsoft.DataFactory/factories/pipelines",
			"apiVersion": "2018-06-01",
			"properties": {
				"activities": [
					{
						"name": "Copy data1",
						"type": "Copy",
						"dependsOn": [],
						"policy": {
							"timeout": "7.00:00:00",
							"retry": 0,
							"retryIntervalInSeconds": 30,
							"secureOutput": false,
							"secureInput": false
						},
						"userProperties": [],
						"typeProperties": {
							"source": {
								"type": "BinarySource",
								"storeSettings": {
									"type": "AzureBlobStorageReadSettings",
									"recursive": true,
									"wildcardFileName": "*.csv",
									"deleteFilesAfterCompletion": false
								},
								"formatSettings": {
									"type": "BinaryReadSettings"
								}
							},
							"sink": {
								"type": "BinarySink",
								"storeSettings": {
									"type": "AzureBlobStorageWriteSettings"
								}
							},
							"enableStaging": false
						},
						"inputs": [
							{
								"referenceName": "ParametersExpressionsLab2Source",
								"type": "DatasetReference",
								"parameters": {}
							}
						],
						"outputs": [
							{
								"referenceName": "ParametersExpressionsLab2Sink",
								"type": "DatasetReference",
								"parameters": {
									"FileName": {
										"value": "@{pipeline().TriggerTime}.zip",
										"type": "Expression"
									}
								}
							}
						]
					}
				],
				"policy": {
					"elapsedTimeMetric": {},
					"cancelAfter": {}
				},
				"folder": {
					"name": "ParametersExpressionsLab"
				},
				"annotations": [],
				"lastPublishTime": "2021-07-02T07:26:56Z"
			},
			"dependsOn": []
		},
		{
			"name": "[concat(parameters('factoryName'), '/TEST')]",
			"type": "Microsoft.DataFactory/factories/pipelines",
			"apiVersion": "2018-06-01",
			"properties": {
				"activities": [
					{
						"name": "Copy data1",
						"type": "Copy",
						"dependsOn": [],
						"policy": {
							"timeout": "0.12:00:00",
							"retry": 0,
							"retryIntervalInSeconds": 30,
							"secureOutput": false,
							"secureInput": false
						},
						"userProperties": [],
						"typeProperties": {
							"source": {
								"type": "DelimitedTextSource",
								"storeSettings": {
									"type": "AzureBlobStorageReadSettings",
									"recursive": true,
									"enablePartitionDiscovery": false
								},
								"formatSettings": {
									"type": "DelimitedTextReadSettings"
								}
							},
							"sink": {
								"type": "DelimitedTextSink",
								"storeSettings": {
									"type": "AzureBlobStorageWriteSettings"
								},
								"formatSettings": {
									"type": "DelimitedTextWriteSettings",
									"quoteAllText": true,
									"fileExtension": ".txt"
								}
							},
							"enableStaging": false,
							"translator": {
								"type": "TabularTranslator",
								"typeConversion": true,
								"typeConversionSettings": {
									"allowDataTruncation": true,
									"treatBooleanAsNumber": false
								}
							}
						},
						"inputs": [
							{
								"referenceName": "AzureBlobDataset",
								"type": "DatasetReference",
								"parameters": {}
							}
						],
						"outputs": [
							{
								"referenceName": "AzureBlobDataset",
								"type": "DatasetReference",
								"parameters": {}
							}
						]
					}
				],
				"policy": {
					"elapsedTimeMetric": {},
					"cancelAfter": {}
				},
				"annotations": []
			},
			"dependsOn": []
		},
		{
			"name": "[concat(parameters('factoryName'), '/parquettest')]",
			"type": "Microsoft.DataFactory/factories/pipelines",
			"apiVersion": "2018-06-01",
			"properties": {
				"activities": [
					{
						"name": "Copy data1",
						"type": "Copy",
						"dependsOn": [],
						"policy": {
							"timeout": "0.12:00:00",
							"retry": 0,
							"retryIntervalInSeconds": 30,
							"secureOutput": false,
							"secureInput": false
						},
						"userProperties": [],
						"typeProperties": {
							"source": {
								"type": "ParquetSource",
								"storeSettings": {
									"type": "AzureBlobStorageReadSettings",
									"recursive": true,
									"enablePartitionDiscovery": false
								}
							},
							"sink": {
								"type": "ParquetSink",
								"storeSettings": {
									"type": "AzureBlobStorageWriteSettings"
								},
								"formatSettings": {
									"type": "ParquetWriteSettings"
								}
							},
							"enableStaging": false,
							"translator": {
								"type": "TabularTranslator",
								"typeConversion": true,
								"typeConversionSettings": {
									"allowDataTruncation": true,
									"treatBooleanAsNumber": false
								}
							}
						},
						"inputs": [
							{
								"referenceName": "Parquet1",
								"type": "DatasetReference",
								"parameters": {}
							}
						],
						"outputs": [
							{
								"referenceName": "Parquetoutput",
								"type": "DatasetReference",
								"parameters": {}
							}
						]
					}
				],
				"policy": {
					"elapsedTimeMetric": {},
					"cancelAfter": {}
				},
				"annotations": [],
				"lastPublishTime": "2022-10-19T10:43:49Z"
			},
			"dependsOn": []
		},
		{
			"name": "[concat(parameters('factoryName'), '/AzurePractice001')]",
			"type": "Microsoft.DataFactory/factories/datasets",
			"apiVersion": "2018-06-01",
			"properties": {
				"linkedServiceName": {
					"referenceName": "twadfpractice",
					"type": "LinkedServiceReference"
				},
				"annotations": [],
				"type": "AzureSqlTable",
				"schema": [
					{
						"name": "CustomerID",
						"type": "int",
						"precision": 10
					},
					{
						"name": "Name",
						"type": "nchar"
					}
				],
				"typeProperties": {
					"schema": "dbo",
					"table": "Customer"
				}
			},
			"dependsOn": []
		},
		{
			"name": "[concat(parameters('factoryName'), '/AzureSQLDB')]",
			"type": "Microsoft.DataFactory/factories/datasets",
			"apiVersion": "2018-06-01",
			"properties": {
				"linkedServiceName": {
					"referenceName": "AzureSQLDB_SELFHOSTIR",
					"type": "LinkedServiceReference"
				},
				"annotations": [],
				"type": "AzureSqlTable",
				"schema": [
					{
						"name": "CustomerKey",
						"type": "int",
						"precision": 10
					},
					{
						"name": "GeographyKey",
						"type": "int",
						"precision": 10
					},
					{
						"name": "CustomerAlternateKey",
						"type": "nvarchar"
					},
					{
						"name": "Title",
						"type": "nvarchar"
					},
					{
						"name": "FirstName",
						"type": "nvarchar"
					},
					{
						"name": "MiddleName",
						"type": "nvarchar"
					},
					{
						"name": "LastName",
						"type": "nvarchar"
					},
					{
						"name": "NameStyle",
						"type": "bit"
					},
					{
						"name": "BirthDate",
						"type": "date"
					},
					{
						"name": "MaritalStatus",
						"type": "nchar"
					},
					{
						"name": "Suffix",
						"type": "nvarchar"
					},
					{
						"name": "Gender",
						"type": "nvarchar"
					},
					{
						"name": "EmailAddress",
						"type": "nvarchar"
					},
					{
						"name": "YearlyIncome",
						"type": "money",
						"precision": 19,
						"scale": 4
					},
					{
						"name": "TotalChildren",
						"type": "tinyint",
						"precision": 3
					},
					{
						"name": "NumberChildrenAtHome",
						"type": "tinyint",
						"precision": 3
					},
					{
						"name": "EnglishEducation",
						"type": "nvarchar"
					},
					{
						"name": "SpanishEducation",
						"type": "nvarchar"
					},
					{
						"name": "FrenchEducation",
						"type": "nvarchar"
					},
					{
						"name": "EnglishOccupation",
						"type": "nvarchar"
					},
					{
						"name": "SpanishOccupation",
						"type": "nvarchar"
					},
					{
						"name": "FrenchOccupation",
						"type": "nvarchar"
					},
					{
						"name": "HouseOwnerFlag",
						"type": "nchar"
					},
					{
						"name": "NumberCarsOwned",
						"type": "tinyint",
						"precision": 3
					},
					{
						"name": "AddressLine1",
						"type": "nvarchar"
					},
					{
						"name": "AddressLine2",
						"type": "nvarchar"
					},
					{
						"name": "Phone",
						"type": "nvarchar"
					},
					{
						"name": "DateFirstPurchase",
						"type": "date"
					},
					{
						"name": "CommuteDistance",
						"type": "nvarchar"
					}
				],
				"typeProperties": {
					"schema": "dbo",
					"table": "DimCustomer"
				}
			},
			"dependsOn": []
		},
		{
			"name": "[concat(parameters('factoryName'), '/Binary1')]",
			"type": "Microsoft.DataFactory/factories/datasets",
			"apiVersion": "2018-06-01",
			"properties": {
				"linkedServiceName": {
					"referenceName": "AzureBlobStorage1",
					"type": "LinkedServiceReference"
				},
				"annotations": [],
				"type": "Binary",
				"typeProperties": {
					"location": {
						"type": "AzureBlobStorageLocation",
						"container": "adftutorial"
					}
				}
			},
			"dependsOn": []
		},
		{
			"name": "[concat(parameters('factoryName'), '/Binary2')]",
			"type": "Microsoft.DataFactory/factories/datasets",
			"apiVersion": "2018-06-01",
			"properties": {
				"linkedServiceName": {
					"referenceName": "AzureBlobStorage1",
					"type": "LinkedServiceReference"
				},
				"annotations": [],
				"type": "Binary",
				"typeProperties": {
					"location": {
						"type": "AzureBlobStorageLocation",
						"container": "output"
					}
				}
			},
			"dependsOn": []
		},
		{
			"name": "[concat(parameters('factoryName'), '/BinarySinkFileStore')]",
			"type": "Microsoft.DataFactory/factories/datasets",
			"apiVersion": "2018-06-01",
			"properties": {
				"description": "Connection to your destination data store.",
				"linkedServiceName": {
					"referenceName": "AzureBlobStorage1",
					"type": "LinkedServiceReference"
				},
				"parameters": {
					"container": {
						"type": "string"
					},
					"directory": {
						"type": "string"
					}
				},
				"annotations": [],
				"type": "Binary",
				"typeProperties": {
					"location": {
						"type": "AzureBlobStorageLocation",
						"folderPath": {
							"value": "@dataset().directory",
							"type": "Expression"
						},
						"container": {
							"value": "@dataset().container",
							"type": "Expression"
						}
					}
				}
			},
			"dependsOn": []
		},
		{
			"name": "[concat(parameters('factoryName'), '/Customer1')]",
			"type": "Microsoft.DataFactory/factories/datasets",
			"apiVersion": "2018-06-01",
			"properties": {
				"linkedServiceName": {
					"referenceName": "twadfpractice",
					"type": "LinkedServiceReference"
				},
				"annotations": [],
				"type": "AzureSqlTable",
				"schema": [
					{
						"name": "CustomerID",
						"type": "int",
						"precision": 10
					},
					{
						"name": "Name",
						"type": "nchar"
					}
				],
				"typeProperties": {
					"schema": "dbo",
					"table": "Customer1"
				}
			},
			"dependsOn": []
		},
		{
			"name": "[concat(parameters('factoryName'), '/DS_INSIGHT_ADLS_BinaryFolder')]",
			"type": "Microsoft.DataFactory/factories/datasets",
			"apiVersion": "2018-06-01",
			"properties": {
				"linkedServiceName": {
					"referenceName": "LS_insight_ADLS_Data_Transfer",
					"type": "LinkedServiceReference"
				},
				"parameters": {
					"Folder": {
						"type": "string"
					}
				},
				"annotations": [],
				"type": "Binary",
				"typeProperties": {
					"location": {
						"type": "AzureBlobFSLocation",
						"folderPath": {
							"value": "@dataset().Folder",
							"type": "Expression"
						}
					}
				}
			},
			"dependsOn": []
		},
		{
			"name": "[concat(parameters('factoryName'), '/DS_INSIGHT_ADLS_LegacyBlob')]",
			"type": "Microsoft.DataFactory/factories/datasets",
			"apiVersion": "2018-06-01",
			"properties": {
				"linkedServiceName": {
					"referenceName": "LS_insight_ADLS_DMZ_Legacy",
					"type": "LinkedServiceReference",
					"parameters": {
						"Account": {
							"value": "@dataset().Account",
							"type": "Expression"
						}
					}
				},
				"parameters": {
					"Container": {
						"type": "string"
					},
					"Account": {
						"type": "string"
					}
				},
				"annotations": [],
				"type": "Binary",
				"typeProperties": {
					"location": {
						"type": "AzureBlobFSLocation",
						"fileSystem": {
							"value": "@dataset().Container",
							"type": "Expression"
						}
					}
				}
			},
			"dependsOn": []
		},
		{
			"name": "[concat(parameters('factoryName'), '/DataMovementLabDimCustomer')]",
			"type": "Microsoft.DataFactory/factories/datasets",
			"apiVersion": "2018-06-01",
			"properties": {
				"linkedServiceName": {
					"referenceName": "DataMovementLabAzureSQL",
					"type": "LinkedServiceReference"
				},
				"folder": {
					"name": "Data Movement Lab"
				},
				"annotations": [],
				"type": "AzureSqlTable",
				"schema": [
					{
						"name": "CustomerKey",
						"type": "int",
						"precision": 10
					},
					{
						"name": "GeographyKey",
						"type": "int",
						"precision": 10
					},
					{
						"name": "CustomerAlternateKey",
						"type": "nvarchar"
					},
					{
						"name": "Title",
						"type": "nvarchar"
					},
					{
						"name": "FirstName",
						"type": "nvarchar"
					},
					{
						"name": "MiddleName",
						"type": "nvarchar"
					},
					{
						"name": "LastName",
						"type": "nvarchar"
					},
					{
						"name": "NameStyle",
						"type": "bit"
					},
					{
						"name": "BirthDate",
						"type": "date"
					},
					{
						"name": "MaritalStatus",
						"type": "nchar"
					},
					{
						"name": "Suffix",
						"type": "nvarchar"
					},
					{
						"name": "Gender",
						"type": "nvarchar"
					},
					{
						"name": "EmailAddress",
						"type": "nvarchar"
					},
					{
						"name": "YearlyIncome",
						"type": "money",
						"precision": 19,
						"scale": 4
					},
					{
						"name": "TotalChildren",
						"type": "tinyint",
						"precision": 3
					},
					{
						"name": "NumberChildrenAtHome",
						"type": "tinyint",
						"precision": 3
					},
					{
						"name": "EnglishEducation",
						"type": "nvarchar"
					},
					{
						"name": "SpanishEducation",
						"type": "nvarchar"
					},
					{
						"name": "FrenchEducation",
						"type": "nvarchar"
					},
					{
						"name": "EnglishOccupation",
						"type": "nvarchar"
					},
					{
						"name": "SpanishOccupation",
						"type": "nvarchar"
					},
					{
						"name": "FrenchOccupation",
						"type": "nvarchar"
					},
					{
						"name": "HouseOwnerFlag",
						"type": "nchar"
					},
					{
						"name": "NumberCarsOwned",
						"type": "tinyint",
						"precision": 3
					},
					{
						"name": "AddressLine1",
						"type": "nvarchar"
					},
					{
						"name": "AddressLine2",
						"type": "nvarchar"
					},
					{
						"name": "Phone",
						"type": "nvarchar"
					},
					{
						"name": "DateFirstPurchase",
						"type": "date"
					},
					{
						"name": "CommuteDistance",
						"type": "nvarchar"
					}
				],
				"typeProperties": {
					"schema": "dbo",
					"table": "DimCustomer"
				}
			},
			"dependsOn": []
		},
		{
			"name": "[concat(parameters('factoryName'), '/SELFHOSTNODE1_DIMCUSTOMER')]",
			"type": "Microsoft.DataFactory/factories/datasets",
			"apiVersion": "2018-06-01",
			"properties": {
				"linkedServiceName": {
					"referenceName": "SELFHOSTNODE1_AdventureWorksDW2016",
					"type": "LinkedServiceReference"
				},
				"folder": {
					"name": "UntilActivity"
				},
				"annotations": [],
				"type": "SqlServerTable",
				"schema": [
					{
						"name": "CustomerKey",
						"type": "int",
						"precision": 10
					},
					{
						"name": "GeographyKey",
						"type": "int",
						"precision": 10
					},
					{
						"name": "CustomerAlternateKey",
						"type": "nvarchar"
					},
					{
						"name": "Title",
						"type": "nvarchar"
					},
					{
						"name": "FirstName",
						"type": "nvarchar"
					},
					{
						"name": "MiddleName",
						"type": "nvarchar"
					},
					{
						"name": "LastName",
						"type": "nvarchar"
					},
					{
						"name": "NameStyle",
						"type": "bit"
					},
					{
						"name": "BirthDate",
						"type": "date"
					},
					{
						"name": "MaritalStatus",
						"type": "nchar"
					},
					{
						"name": "Suffix",
						"type": "nvarchar"
					},
					{
						"name": "Gender",
						"type": "nvarchar"
					},
					{
						"name": "EmailAddress",
						"type": "nvarchar"
					},
					{
						"name": "YearlyIncome",
						"type": "money",
						"precision": 19,
						"scale": 4
					},
					{
						"name": "TotalChildren",
						"type": "tinyint",
						"precision": 3
					},
					{
						"name": "NumberChildrenAtHome",
						"type": "tinyint",
						"precision": 3
					},
					{
						"name": "EnglishEducation",
						"type": "nvarchar"
					},
					{
						"name": "SpanishEducation",
						"type": "nvarchar"
					},
					{
						"name": "FrenchEducation",
						"type": "nvarchar"
					},
					{
						"name": "EnglishOccupation",
						"type": "nvarchar"
					},
					{
						"name": "SpanishOccupation",
						"type": "nvarchar"
					},
					{
						"name": "FrenchOccupation",
						"type": "nvarchar"
					},
					{
						"name": "HouseOwnerFlag",
						"type": "nchar"
					},
					{
						"name": "NumberCarsOwned",
						"type": "tinyint",
						"precision": 3
					},
					{
						"name": "AddressLine1",
						"type": "nvarchar"
					},
					{
						"name": "AddressLine2",
						"type": "nvarchar"
					},
					{
						"name": "Phone",
						"type": "nvarchar"
					},
					{
						"name": "DateFirstPurchase",
						"type": "date"
					},
					{
						"name": "CommuteDistance",
						"type": "nvarchar"
					}
				],
				"typeProperties": {
					"schema": "dbo",
					"table": "DimCustomer"
				}
			},
			"dependsOn": []
		},
		{
			"name": "[concat(parameters('factoryName'), '/SqlServerDataset')]",
			"type": "Microsoft.DataFactory/factories/datasets",
			"apiVersion": "2018-06-01",
			"properties": {
				"linkedServiceName": {
					"referenceName": "SqlServerLinkedService",
					"type": "LinkedServiceReference"
				},
				"annotations": [],
				"type": "SqlServerTable",
				"schema": [
					{
						"name": "ID",
						"type": "int",
						"precision": 10
					},
					{
						"name": "FirstName",
						"type": "varchar"
					},
					{
						"name": "LastName",
						"type": "varchar"
					}
				],
				"typeProperties": {
					"schema": "dbo",
					"table": "emp"
				}
			},
			"dependsOn": []
		},
		{
			"name": "[concat(parameters('factoryName'), '/WatermarkDataset')]",
			"type": "Microsoft.DataFactory/factories/datasets",
			"apiVersion": "2018-06-01",
			"properties": {
				"linkedServiceName": {
					"referenceName": "SELFHOSTNODE1",
					"type": "LinkedServiceReference"
				},
				"folder": {
					"name": "incrementalcopy"
				},
				"annotations": [],
				"type": "SqlServerTable",
				"schema": [
					{
						"name": "TableName",
						"type": "varchar"
					},
					{
						"name": "WatermarkValue",
						"type": "datetime",
						"precision": 23,
						"scale": 3
					}
				],
				"typeProperties": {
					"schema": "dbo",
					"table": "watermarktable"
				}
			},
			"dependsOn": []
		}
	]
}